{
  "schemaVersion": 1,
  "id": "api.cors-origin",
  "type": "foundation",
  "title": "CORS 与 Origin：浏览器跨域访问边界",
  "domain": "api",
  "track": "network-api",
  "skills": ["api.integration", "security.governance"],
  "level": "intermediate",
  "order": 68,
  "estimatedMinutes": 10,
  "content": {
    "simpleExplanation": "CORS 是浏览器依据响应头执行的跨源读取策略，服务端需明确允许的 Origin、方法和头部，但它不能替代 API 自身的认证与授权。",
    "analogy": "CORS 像办公楼规定哪些外部前台可以代领回执，门卫仍会核对每份业务凭据；允许某个前台接收响应，不代表它自动拥有所有房间权限。",
    "technicalExplanation": "浏览器对部分跨源请求先发送预检，服务端返回允许的来源、方法、头部和凭据策略。Origin 包含协议、主机与端口，通配来源不能与凭据随意组合。",
    "example": "FDE 确认合作方请求由后端服务直接发出，没有浏览器、Origin 或预检流量，因此排除了 CORS；脱敏令牌证据显示 audience 正确但缺少读取 scope，修复集中在客户端授权注册。",
    "commonMistakes": "用允许所有来源掩盖配置问题会扩大数据读取面，把 CORS 当作服务端访问控制也会让非浏览器客户端绕过。排障应分别验证预检、实际响应和令牌权限。"
  },
  "relatedCases": ["api-oauth-scope-mismatch-001"]
}
